deltona/__init__.py
deltona/adp.py
deltona/chromium.py
deltona/commands/__init__.py
deltona/commands/admin.py
deltona/commands/desktop.py
deltona/commands/git.py
deltona/commands/media.py
deltona/commands/misc.py
deltona/commands/string.py
deltona/commands/wine.py
deltona/commands/www.py
deltona/constants.py
deltona/gentoo.py
deltona/git.py
deltona/io.py
deltona/media.py
deltona/naming.py
deltona/py.typed
deltona/string.py
deltona/system.py
deltona/typing.py
deltona/ultraiso.py
deltona/utils.py
deltona/windows.py
deltona/www.py
deltona-0.0.2.dist-info/LICENSE.txt
deltona-0.0.2.dist-info/METADATA
deltona-0.0.2.dist-info/WHEEL
deltona-0.0.2.dist-info/entry_points.txt
deltona-0.0.2.dist-info/RECORD
