Metadata-Version: 2.3
Name: deltona
Version: 0.0.2
Summary: A lot of uncategorised utilities.
License: MIT
Keywords: bluetooth,command line,file management,git,multimedia
Author: Andrew Udvare
Author-email: audvare@gmail.com
Requires-Python: >=3.10,<3.14
Classifier: Development Status :: 4 - Beta
Classifier: Environment :: Console
Classifier: Intended Audience :: Developers
Classifier: Intended Audience :: End Users/Desktop
Classifier: Intended Audience :: Information Technology
Classifier: Intended Audience :: System Administrators
Classifier: Operating System :: MacOS
Classifier: Operating System :: Microsoft :: Windows
Classifier: Operating System :: POSIX :: Linux
Classifier: Programming Language :: Python :: 3.12
Classifier: Programming Language :: Python :: 3.13
Classifier: Programming Language :: Python
Classifier: Topic :: Desktop Environment :: K Desktop Environment (KDE)
Classifier: Topic :: Desktop Environment
Classifier: Topic :: File Formats
Classifier: Topic :: Games/Entertainment
Classifier: Topic :: Internet :: WWW/HTTP :: Browsers
Classifier: Topic :: Multimedia
Classifier: Topic :: System :: Hardware
Classifier: Topic :: System :: Systems Administration
Classifier: Topic :: Utilities
Classifier: Typing :: Typed
Provides-Extra: admin
Provides-Extra: desktop
Provides-Extra: git
Provides-Extra: media
Provides-Extra: string
Provides-Extra: wine
Provides-Extra: www
Requires-Dist: beautifulsoup4 (>=4.13.4,<5.0.0) ; extra == "www"
Requires-Dist: binaryornot (>=0.4.4,<0.5.0)
Requires-Dist: click (>=8.2.1,<9.0.0)
Requires-Dist: colorlog (>=6.9.0,<7.0.0)
Requires-Dist: gitpython (>=3.1.44,<4.0.0) ; extra == "git"
Requires-Dist: html5lib (>=1.1,<2.0) ; extra == "www"
Requires-Dist: keyring (>=25.6.0,<26.0.0)
Requires-Dist: mutagen (>=1.47.0,<2.0.0) ; extra == "media"
Requires-Dist: paramiko (>=3.5.1,<4.0.0) ; extra == "admin"
Requires-Dist: pexpect (>=4.9.0,<5.0.0) ; extra == "wine"
Requires-Dist: pillow (>=11.2.1,<12.0.0) ; extra == "www"
Requires-Dist: platformdirs (>=4.3.8,<5.0.0) ; extra == "media" or extra == "wine"
Requires-Dist: psutil (>=7.0.0,<8.0.0) ; extra == "wine"
Requires-Dist: pydbus (>=0.6.0,<0.7.0) ; (sys_platform == "linux") and (extra == "desktop")
Requires-Dist: pygithub (>=2.6.1,<3.0.0) ; extra == "git"
Requires-Dist: pygobject (>=3.52.3,<4.0.0) ; (sys_platform == "linux") and (extra == "desktop")
Requires-Dist: pyperclip (>=1.9.0,<2.0.0) ; extra == "desktop"
Requires-Dist: python-xz (>=0.5.0,<0.6.0) ; extra == "wine"
Requires-Dist: pyyaml (>=6.0.2,<7.0.0) ; extra == "string"
Requires-Dist: requests (>=2.32.3,<3.0.0)
Requires-Dist: send2trash (>=1.8.3,<2.0.0)
Requires-Dist: typing-extensions (>=4.14.0,<5.0.0)
Requires-Dist: unidecode (>=1.4.0,<2.0.0) ; extra == "string"
Requires-Dist: yt-dlp (>=2025.5.22,<2026.0.0) ; extra == "string"
Project-URL: Documentation, https://deltona.readthedocs.org
Project-URL: Homepage, https://tatsh.github.io/deltona/
Project-URL: Issues, https://github.com/Tatsh/deltona/issues
Project-URL: Repository, https://github.com/Tatsh/deltona
